{
    "id": "beerus",
    "aliases": ["beerus", "god_of_destruction"],
    "essence": "species_alien_deity",
    "prompt_base": "slender feline deity, dusty purple skin, large pointed ears, yellow eyes, maroon silk robe, wide gold obi belt",
    "feature_prompt": "natural skin texture, detailed silk fabric folds, intricate gold trim, subsurface scattering on ears",
    "negative_prompt": "anime, cartoon, drawing, illustration, plastic skin, human face, cat ears, flat lighting, low quality, bare legs, exposed lower body, shorts",
    "weights": { 
        "depth": 0.70,
        "openpose": 0.75
    },
    "denoising_strength": 0.65
}